codificador.v
module codificador (a,b,c,d,m1,m2, m3, m4, m5, reset, ready);
  input wire a,b,c,d,reset, ready;
  output reg m1,m2,m3,m4,m5;

  always @ (*) begin
    if (reset) begin
      m1=0;
      m2=0;
      m3=0;
      m4=0;
      m5=0;
    end // AND =& or =| not = ~\\
    else if(ready) begin
      m1 = (b & ~c) | (~a &  ~c & d) | (~b & c);
      m2 = (~a & b & ~c) | (~a & ~b & c) | (~a & c & ~d);
      m3 = (~a & b) | (~a & c & d);
      m4 = (~a & b) | (a & ~b & ~c & ~d);
      m5 = (a & ~b & ~c) | (~a & b & d) | (~a & b & c);
    end


    end

endmodule

testebench.v
`include "codificador.v"
module testebench();
     reg a,b,c,d,reset,ready;
     wire m1,m2,m3,m4,m5;
     codificador codificador_0(.a(a),.b(b),.c(c),.d(d),.m1(m1),.m2(m2),.m3(m3),.m4(m4),.m5(m5), .reset(reset),.ready(ready));


     initial begin //setando entrada com tabela verdade

      $dumpfile("codificador.vcd");
      $dumpvars(0, testebench);
	
	  $display("Codificador morse");

    
      $monitor("%b%b%b%b = %b%b%b%b%b",a,b,c,d,m1,m2,m3,m4,m5);
      reset=1;
      #1; reset=0;
      #1; ready=0;a=0; b=0; c=0; d=0; ready=1;//0000
      #1; ready=0;a=0; b=0; c=0; d=1;ready=1;
      #1; ready=0;a=0; b=0; c=1; d=0;ready=1;
      #1;ready=0;a=0; b=0; c=1; d=1;ready=1;
      #1; ready=0;a=0;b=1; c=0; d=0;ready=1;
      #1; ready=0;a=0; b=1; c=0; d=1;ready=1;
      #1; ready=0;a=0; b=1; c=1; d=0;ready=1;
      #1; ready=0;a=0; b=1; c=1; d=1;ready=1;
      #1; ready=0;a=1; b=0; c=0; d=0;ready=1;
      #1; ready=0;a=1; b=0; c=0; d=1;ready=1;

      $finish;
      end

endmodule

codificador.vcd
$date
	Wed Oct 10 19:07:15 2018
$end
$version
	Icarus Verilog
$end
$timescale
	1s
$end
$scope module testebench $end
$var wire 1 ! m5 $end
$var wire 1 " m4 $end
$var wire 1 # m3 $end
$var wire 1 $ m2 $end
$var wire 1 % m1 $end
$var reg 1 & a $end
$var reg 1 ' b $end
$var reg 1 ( c $end
$var reg 1 ) d $end
$var reg 1 * ready $end
$var reg 1 + reset $end
$scope module codificador_0 $end
$var wire 1 & a $end
$var wire 1 ' b $end
$var wire 1 ( c $end
$var wire 1 ) d $end
$var wire 1 * ready $end
$var wire 1 + reset $end
$var reg 1 % m1 $end
$var reg 1 $ m2 $end
$var reg 1 # m3 $end
$var reg 1 " m4 $end
$var reg 1 ! m5 $end
$upscope $end
$upscope $end
$enddefinitions $end
#0
$dumpvars
1+
x*
x)
x(
x'
x&
0%
0$
0#
0"
0!
$end
#1
0+
#2
0)
0(
0'
0&
1*
#3
1%
1)
1*
#4
1$
0)
1(
1*
#5
1#
1)
1*
#6
1"
0)
0(
1'
1*
#7
1!
1)
1*
#8
0%
0)
1(
1*
#9
0$
1)
1*
#10
0#
0)
0(
0'
1&
1*
#11
0"
1)
1*
